AUTHORS.rst
CONTRIBUTING.rst
HISTORY.rst
LICENSE
MANIFEST.in
README.rst
setup.cfg
setup.py
e24PaymentPipe/__init__.py
e24PaymentPipe/e24PaymentPipe.py
e24PaymentPipe/exceptions.py
e24PaymentPipe/utils.py
e24PaymentPipe.egg-info/PKG-INFO
e24PaymentPipe.egg-info/SOURCES.txt
e24PaymentPipe.egg-info/dependency_links.txt
e24PaymentPipe.egg-info/not-zip-safe
e24PaymentPipe.egg-info/pbr.json
e24PaymentPipe.egg-info/requires.txt
e24PaymentPipe.egg-info/top_level.txt