Metadata-Version: 1.1
Name: e24PaymentPipe
Version: 1.2.0
Summary: This package provides a Python implementation for ACI's e24PaymentPipe Merchant Gateway
Home-page: https://github.com/burhan/e24PaymentPipe
Author: Burhan Khalid
Author-email: burhan.khalid@gmail.com
License: BSD
Keywords: e24PaymentPipe
Platform: UNKNOWN
Classifier: Development Status :: 5 - Production/Stable
Classifier: Intended Audience :: Developers
Classifier: License :: OSI Approved :: BSD License
Classifier: Natural Language :: English
Classifier: Programming Language :: Python :: 2
Classifier: Programming Language :: Python :: 2.6
Classifier: Programming Language :: Python :: 2.7
Classifier: Programming Language :: Python :: 3.4
